{
  "list": [
    {
      "text": "Kangaroos cannot walk backwards!",
	  "image": "https://upload.wikimedia.org/wikipedia/commons/c/c3/Eastern_grey_kangaroo_dec07_02.jpg",
      "date": "1493586000000"
    },
    {
      "text": "Approximately 11% of people are left handed",
	  "image": "http://www.informationng.com/wp-content/uploads/2016/01/Left-handed-people.jpg",
      "date": "1493499600000"
    },
	{
      "text": "August has the highest percentage of births",
	  "image": "http://textimages.us/august/august02/august-029.jpg",
      "date": "1493499600000"
    },
	{
      "text": "The average person falls asleep in 7 minutes",
	  "image": "",
      "date": "1493499600000"
    },
	{
      "text": "A bear has 42 teeth",
	  "image": "",
      "date": "1493499600000"
    },
	{
      "text": "An ostrich's eye is bigger than its brain",
	  "image": "",
      "date": "1493499600000"
    },
	{
      "text": "Lemons contain more sugar than strawberries",
	  "image": "",
      "date": "1493499600000"
    },
	{
      "text": "85% of plant life is found in the ocean",
	  "image": "",
      "date": "1493499600000"
    },
	{
      "text": "Ralph Lauren's original name was Ralph Lifshitz",
	  "image": "",
      "date": "1493499600000"
    },
	{
      "text": "the Hawaiian alphabet has 13 letters",
	  "image": "",
      "date": "1493499600000"
    },
	{
      "text": "'Topolino' is the name for Mickey Mouse Italy",
	  "image": "",
      "date": "1493499600000"
    },
	{
      "text": "Armadillos have 4 babies at a time and are all the same sex",
	  "image": "",
      "date": "1493499600000"
    },
	{
      "text": "The longest recorded flight of a chicken was 13 seconds",
	  "image": "",
      "date": "1493499600000"
    },
	{
      "text": "The most commonly used letter in the alphabet is E",
	  "image": "",
      "date": "1493499600000"
    },
	{
      "text": "The 3 most common languages in the world are Mandarin Chinese, Spanish and English",
	  "image": "",
      "date": "1493499600000"
    },
	{
      "text": "Dreamt is the only word that ends in mt",
	  "image": "",
      "date": "1493499600000"
	},
	{
      "text": "The first letters of the months July through to November spell JASON",
	  "image": "",
      "date": "1493499600000"
	},
	{
      "text": "A cat has 32 muscles in each ear",
	  "image": "",
      "date": "1493499600000"
	},
	{
      "text": "Elvis's middle name was Aron",
	  "image": "",
      "date": "1493499600000"
	},
	{
      "text": "Goldfish can see both infra-red and ultra-violet light",
	  "image": "",
      "date": "1493499600000"
	},
	{
      "text": "The smallest bones in the human body are found in your ear",
	  "image": "",
      "date": "1493499600000"
	},
	{
      "text": "Cats spend 66% of their life asleep",
	  "image": "",
      "date": "1493499600000"
	},
	{
      "text": "Switzerland eats the most chocolate equating to 10 kilos per person per year",
	  "image": "",
      "date": "1493499600000"
	},
	{
      "text": "Money is the number one thing that couples argue about",
	  "image": "",
      "date": "1493499600000"
	},
	{
      "text": "Macadamia nuts are toxic to dogs",
	  "image": "",
      "date": "1493499600000"
	},
	{
      "text": "When lightning strikes it can reach up to 30,000 degrees celsius (54,000 degrees fahrenheit)",
	  "image": "",
      "date": "1493499600000"
	},
	{
      "text": "Each time you see a full moon you always see the same side",
	  "image": "",
      "date": "1493499600000"
	},
	{
      "text": "Honey is the only natural food which never spoils",
	  "image": "",
      "date": "1493499600000"
	},
	{
      "text": "M&M's chocolate stands for the initials for its inventors Mars and Murrie",
	  "image": "",
      "date": "1493499600000"
	},
	{
      "text": "You burn more calories eating celery than it contains",
	  "image": "",
      "date": "1493499600000"
	},
	{
      "text": "The only continent with no active volcanoes is Australia",
	  "image": "",
      "date": "1493499600000"
	},
	{
      "text": "The longest street in the world is Yonge street in Toronto Canada measuring 1,896 km (1,178 miles)",
	  "image": "",
      "date": "1493499600000"
	},
	{
      "text": "About 90% of the worlds population kisses",
	  "image": "",
      "date": "1493499600000"
	},
	{
      "text": "The Internet was originally called ARPANet (Advanced Research Projects Agency Network) designed by the US department of defense",
	  "image": "",
      "date": "1493499600000"
	},
	{
      "text": "The fortune cookie was invented in San Francisco",
	  "image": "",
      "date": "1493499600000"
	},
	{
      "text": "Koalas sleep around 18 hours a day",
	  "image": "",
      "date": "1493499600000"
	},
	{
      "text": "All insects have 6 legs",
	  "image": "",
      "date": "1493499600000"
	},
	{
      "text": "The croissant was invented in Austria",
	  "image": "",
      "date": "1493499600000"
	},
	{
      "text": "In eastern Africa you can buy beer brewed from bananas",
	  "image": "",
      "date": "1493499600000"
	},
	{
      "text": "African Grey Parrots have vocabularies of over 200 words",
	  "image": "",
      "date": "1493499600000"
	},
	{
      "text": "Australia was originally called New Holland",
	  "image": "",
      "date": "1493499600000"
	},
	{
      "text": "the sentence 'the quick brown fox jumps over the lazy dog' uses every letter in the English alphabet",
	  "image": "",
      "date": "1493499600000"
	},
	{
      "text": "Your foot has 26 bones in it",
	  "image": "",
      "date": "1493499600000"
	},
	{
      "text": "The average human brain contains around 78% water",
	  "image": "",
      "date": "1493499600000"
	},
	{
      "text": "Sponges hold more cold water than hot",
	  "image": "",
      "date": "1493499600000"
	},
	{
      "text": "Fire usually moves faster uphill than downhill",
	  "image": "",
      "date": "1493499600000"
	},
	{
      "text": "Elephants sleep between 4 - 5 hours in 24 period",
	  "image": "",
      "date": "1493499600000"
	},
	{
      "text": "Frogs can't swallow with their eyes open",
	  "image": "",
      "date": "1493499600000"
	},
	{
      "text": "Elephants are the only mammal that can't jump",
	  "image": "",
      "date": "1493499600000"
	},
	{
      "text": "Your tongue is the fastest healing part of your body",
	  "image": "",
      "date": "1493499600000"
	},
	{
      "text": "A 1 minute kiss burns 26 calories",
	  "image": "",
      "date": "1493499600000"
	}
  ]
}
